hnswlib.cpython-310-darwin.so
chroma_hnswlib-0.7.2.dist-info/LICENSE
chroma_hnswlib-0.7.2.dist-info/METADATA
chroma_hnswlib-0.7.2.dist-info/WHEEL
chroma_hnswlib-0.7.2.dist-info/top_level.txt
chroma_hnswlib-0.7.2.dist-info/RECORD
