Metadata-Version: 2.1
Name: chroma-hnswlib
Version: 0.7.2
Summary: Chromas fork of hnswlib
Home-page: https://github.com/chroma-core/hnswlib
Author: Yury Malkov and the original hnswlib authors + Chroma
License-File: LICENSE
